sqlcmd/__init__.py
sqlcmd/connection.py
sqlcmd/exceptions.py
sqlcmd/executor.py
sqlcmd/magic.py
sqlcmd/parser.py
ipython_sqlcmd-0.1.3.dist-info/LICENSE
ipython_sqlcmd-0.1.3.dist-info/METADATA
ipython_sqlcmd-0.1.3.dist-info/WHEEL
ipython_sqlcmd-0.1.3.dist-info/entry_points.txt
ipython_sqlcmd-0.1.3.dist-info/top_level.txt
ipython_sqlcmd-0.1.3.dist-info/RECORD
