Metadata-Version: 2.2
Name: ipython-sqlcmd
Version: 0.1.3
Summary: SQL Command Magic for IPython
Home-page: https://github.com/tensor-works/ipython-sqlcmd
Author: Amadou Wolfgang Cisse
Author-email: amadou.6e@googelmail.com
Keywords: ipython,jupyter,sql,sqlcmd,magic
Classifier: Development Status :: 3 - Alpha
Classifier: Framework :: IPython
Classifier: Intended Audience :: Developers
Classifier: Intended Audience :: Science/Research
Classifier: License :: OSI Approved :: MIT License
Classifier: Programming Language :: Python :: 3
Classifier: Programming Language :: Python :: 3.7
Classifier: Programming Language :: Python :: 3.8
Classifier: Programming Language :: Python :: 3.9
Classifier: Programming Language :: Python :: 3.10
Classifier: Programming Language :: Python :: 3.11
Classifier: Topic :: Database
Classifier: Topic :: Software Development :: Libraries :: Python Modules
Requires-Python: >=3.7
License-File: LICENSE
Requires-Dist: ipython>=7.0.0
Requires-Dist: pandas>=1.0.0
Dynamic: author
Dynamic: author-email
Dynamic: classifier
Dynamic: description
Dynamic: description-content-type
Dynamic: home-page
Dynamic: keywords
Dynamic: requires-dist
Dynamic: requires-python
Dynamic: summary
